MANIFEST.in
README.rst
setup.py
src/rfcde/Forest.cpp
src/rfcde/Forest.h
src/rfcde/ForestWrapper.cpp
src/rfcde/ForestWrapper.pyx
src/rfcde/Node.cpp
src/rfcde/Node.h
src/rfcde/Split.cpp
src/rfcde/Split.h
src/rfcde/Tree.cpp
src/rfcde/Tree.h
src/rfcde/__init__.py
src/rfcde/basis_functions.py
src/rfcde/core.py
src/rfcde/helpers.cpp
src/rfcde/helpers.h
src/rfcde/kde.py
src/rfcde/weighted_quantile.py
src/rfcde.egg-info/PKG-INFO
src/rfcde.egg-info/SOURCES.txt
src/rfcde.egg-info/dependency_links.txt
src/rfcde.egg-info/not-zip-safe
src/rfcde.egg-info/requires.txt
src/rfcde.egg-info/top_level.txt