Metadata-Version: 1.2
Name: rfcde
Version: 0.3.2
Summary: Fits random forest conditional density estimate using conditional density loss for splits.
Home-page: https://github.com/tpospisi/rfcde/python
Author: Taylor Pospisil
Author-email: tpospisi@andrew.cmu.edu
Maintainer: tpospisi@andrew.cmu.edu
License: MIT
Keywords: conditional density estimation,random forests
Platform: UNKNOWN
Classifier: License :: OSI Approved :: MIT License
Classifier: Topic :: Scientific/Engineering :: Artificial Intelligence
Classifier: Programming Language :: Python :: 2.7
Classifier: Programming Language :: Python :: 3.7
Classifier: Programming Language :: Cython
Classifier: Programming Language :: C++
Requires-Python: >=2.7
